{
  "contracts": {
    "Voting": "./cadence/contracts/Voting.cdc",
    "VotingToken": "./cadence/contracts/VotingToken.cdc"
  },
  "networks": {
    "emulator": "127.0.0.1:3569",
    "mainnet": "access.mainnet.nodes.onflow.org:9000",
    "testnet": "access.devnet.nodes.onflow.org:9000"
  },
  "accounts": {
    "emulator-account": {
      "address": "f8d6e0586b0a20c7",
      "key": "8e9c05074abb937e5f265c92ce2b49d3774418f7b1dd6f9db3665eebd610ef25"
    }
  },
  "deployments": {
    "emulator": {
      "emulator-account": ["Voting"]
    }
  }
}
